[
    {
        "threadID": "4699505116797365",
        "shortcuts": [
            {
                "id": "moyImSHylE",
                "input": "Duu pro",
                "output": "Quá là pro luôn"
            },
            {
                "id": "SOiFuyAzBY",
                "input": "Duu ngu",
                "output": "Ngu cc Duu pro vc Idol của lòng em"
            },
            {
                "id": "rZUqmwGQRX",
                "input": "momo",
                "output": "0917148616 - MOMO - NGUYỄN NHƯ VŨ"
            },
            {
                "id": "WbTwslycAK",
                "input": "stk",
                "output": "1018007857 - VCB - NGUYỄN NHƯ VŨ"
            },
            {
                "id": "DMnGPJfvzk",
                "input": "donate",
                "output": "0917148616 - MOMO - NGUYỄN NHƯ VŨ\n1018007857 - VCB - NGUYỄN NHƯ VŨ"
            }
        ]
    }
]